xproxy/__init__.py
xproxy/manager/__init__.py
xproxy/manager/base.py
xproxy/manager/duomi.py
xproxy/server.py
xproxy-0.1.0.dist-info/LICENSE
xproxy-0.1.0.dist-info/METADATA
xproxy-0.1.0.dist-info/WHEEL
xproxy-0.1.0.dist-info/RECORD
