Metadata-Version: 2.1
Name: xproxy
Version: 0.1.0
Summary: My Awesome Project!
License: MIT
Author: Author
Author-email: author@example.com
Requires-Python: >=3.10,<4.0
Classifier: License :: OSI Approved :: MIT License
Classifier: Operating System :: OS Independent
Classifier: Programming Language :: Python :: 3
Classifier: Programming Language :: Python :: 3.10
Classifier: Programming Language :: Python :: 3.11
Classifier: Programming Language :: Python :: 3.12
Classifier: Programming Language :: Python :: 3.13
Requires-Dist: pydantic (>=2.9.2,<3.0.0)
Requires-Dist: requests (>=2.32.3,<3.0.0)
